files_from_tmpl/__init__.py
files_from_tmpl/files_from_tmpl.py
files_from_tmpl-0.0.4.dist-info/LICENSE
files_from_tmpl-0.0.4.dist-info/METADATA
files_from_tmpl-0.0.4.dist-info/WHEEL
files_from_tmpl-0.0.4.dist-info/top_level.txt
files_from_tmpl-0.0.4.dist-info/RECORD
